Temp5/Allimp.py
Temp5/Mainpro.py
Temp5/TEMP5.py
Temp5/__init__.py
Temp5/__main__.py
Temp5/requirements.txt
Temp5/setup2.py
Temp5/update.py
Temp5/AI/Analiz.py
Temp5/AI/DBgen.py
Temp5/AI/Generats.py
Temp5/AI/OpnSrc.py
Temp5/AI/__init__.py
Temp5/AI/DL/TmpTest.py
Temp5/AI/DL/__init__.py
Temp5/AI/ML/ConMatrix.py
Temp5/AI/ML/DLPanel.py
Temp5/AI/ML/MLUtility.py
Temp5/AI/ML/SLPanel.py
Temp5/AI/ML/__init__.py
Temp5/AI/Test/AppTest.py
Temp5/AI/Test/__init__.py
Temp5/Config/Init.py
Temp5/Config/MLmethod.ini
Temp5/Config/__init__.py
Temp5/Config/option.ini
Temp5/Config/system1.ini
Temp5/DCC1/AuiPan2.py
Temp5/DCC1/DBDev2.py
Temp5/DCC1/ListPro2.py
Temp5/DCC1/MLDev2.py
Temp5/DCC1/MenuDev2.py
Temp5/DCC1/ProgDev2.py
Temp5/DCC1/Proper2.py
Temp5/DCC1/ToolBar2.py
Temp5/DCC1/__init__.py
Temp5/Database/Menu2.db
Temp5/Database/MenuSet2.py
Temp5/Database/PostGet.py
Temp5/Database/PostGet2.py
Temp5/Database/__init__.py
Temp5/Database/dbinterface.py
Temp5/Database/srcsql.py
Temp5/Database/wxsq.py
Temp5/Database/sqls/Createmenu.sql
Temp5/Database/sqls/__init__.py
Temp5/Fount/Allimp.py
Temp5/Fount/Createmenu.sql
Temp5/Fount/MLmethod.ini
Temp5/Fount/Mainpro.py
Temp5/Fount/option.ini
Temp5/Fount/requirements.txt
Temp5/Fount/system1.ini
Temp5/Fount/update.py
Temp5/GUI/BG2.py
Temp5/GUI/MainMenu2.py
Temp5/GUI/MainTool.py
Temp5/GUI/Start.py
Temp5/GUI/__init__.py
Temp5/GUI/proman.py
Temp5/GUI/window2.py
Temp5/GUI/API/SamPnl.py
Temp5/GUI/API/SamPnl2.py
Temp5/GUI/API/__init__.py
Temp5/GUI/AuiPanel/PAui.py
Temp5/GUI/AuiPanel/__init__.py
Temp5/GUI/AuiPanel/tempane.py
Temp5/GUI/Main/DBv1.py
Temp5/GUI/Main/MDv1.py
Temp5/GUI/Main/MLv1.py
Temp5/GUI/Main/PAv1.py
Temp5/GUI/Main/PGv1.py
Temp5/GUI/Main/PPv1.py
Temp5/GUI/Main/TBv1.py
Temp5/GUI/Main/TPv1.py
Temp5/GUI/Main/__init__.py
Temp5/GUI/Temp/Demo.py
Temp5/GUI/Temp/Muntitle.py
Temp5/GUI/Temp/__init__.py
Temp5/GUI/Temp/untitle.py
Temp5/Logs/__init__.py
Temp5/Res/Allicons.py
Temp5/Res/__init__.py
Temp5/Res/Fonts/__init__.py
Temp5/Res/Icons/__init__.py
Temp5-1.1.1.dist-info/LICENCE.txt
Temp5-1.1.1.dist-info/METADATA
Temp5-1.1.1.dist-info/WHEEL
Temp5-1.1.1.dist-info/top_level.txt
Temp5-1.1.1.dist-info/RECORD
