Metadata-Version: 2.1
Name: Temp5
Version: 1.1.1
Summary: ML PreLibrary Toolkit
Home-page: https://github.com/Srcfount/Temp5/
Author: Pooya Ghiami
Author-email: Pooya Ghiami <pooyagheyami@gmail.com>
License: MIT
Project-URL: Homepage, https://github.com/Srcfount/Temp5/
Project-URL: Bug Tracker, https://github.com/Srcfount/Temp5/issues
Keywords: MACHINELEARNING GUI SQL
Classifier: Programming Language :: Python :: 3
Classifier: License :: OSI Approved :: MIT License
Classifier: Operating System :: OS Independent
Requires-Python: >=3.7
License-File: LICENCE.txt
Requires-Dist: wxPython
